README.md
setup.py
sys_info
npio/__init__.py
npio.egg-info/PKG-INFO
npio.egg-info/SOURCES.txt
npio.egg-info/dependency_links.txt
npio.egg-info/top_level.txt
source/boardtype.c
source/boardtype.h
source/c_gpio.c
source/c_gpio.h
source/common.c
source/common.h
source/constants.c
source/constants.h
source/cpuinfo.c
source/cpuinfo.h
source/event_gpio.c
source/event_gpio.h
source/py_gpio.c
source/py_module_name.h
source/py_pwm.c
source/py_pwm.h
source/soft_pwm.c
source/soft_pwm.h
test/test_gpio_function.py