Metadata-Version: 2.1
Name: npio
Version: 0.1.77
Summary: Module to control NanoPi GPIO channels
Home-page: https://github.com/leftradio/npio
Author: Vladislav Kamenev
Author-email: vladislav@inorbit.com
License: UNKNOWN
Keywords: NanoPi GPIO
Platform: UNKNOWN
Classifier: Development Status :: 4 - Beta
Classifier: Operating System :: POSIX :: Linux
Classifier: Programming Language :: Python :: 3
Classifier: Topic :: Software Development
Classifier: Topic :: Home Automation
Classifier: Topic :: System :: Hardware
